{
  "$schema": "https://json-schema.org/draft/2020-12/schema",
  "title": "single-work-analysis work card",
  "type": "object",
  "required": [
    "platform",
    "platform_work_id",
    "platform_author_id",
    "author_handle",
    "caption_raw",
    "work_modality",
    "published_date",
    "primary_text",
    "primary_text_source"
  ],
  "properties": {
    "platform": { "type": "string", "minLength": 1 },
    "platform_work_id": { "type": "string", "minLength": 1 },
    "platform_author_id": { "type": "string", "minLength": 1 },
    "author_handle": { "type": "string" },
    "title": { "type": "string" },
    "caption_raw": { "type": "string" },
    "work_modality": { "type": "string", "enum": ["video", "text"] },
    "published_date": { "type": "string" },
    "digg_count": { "type": "integer", "minimum": 0 },
    "comment_count": { "type": "integer", "minimum": 0 },
    "collect_count": { "type": "integer", "minimum": 0 },
    "share_count": { "type": "integer", "minimum": 0 },
    "play_count": { "type": ["integer", "null"], "minimum": 0 },
    "cover_image": { "type": "string" },
    "source_url": { "type": "string" },
    "share_url": { "type": "string" },
    "primary_text": { "type": "string" },
    "primary_text_source": { "type": "string", "enum": ["asr_clean", "caption_raw"] },
    "asr_raw": { "type": "string" },
    "video_download_url": { "type": "string" }
  },
  "additionalProperties": true
}
